tensorboard_projects/__init__.py
tensorboard_projects/cli.py
tensorboard_projects/version.py
tensorboard_projects/dashboard/__init__.py
tensorboard_projects/dashboard/tensorboard.py
tensorboard_projects/server/__init__.py
tensorboard_projects/server/handlers.py
tensorboard_projects/server/js/build/asset-manifest.json
tensorboard_projects/server/js/build/env.js
tensorboard_projects/server/js/build/favicon.ico
tensorboard_projects/server/js/build/index.html
tensorboard_projects/server/js/build/logo192.png
tensorboard_projects/server/js/build/logo512.png
tensorboard_projects/server/js/build/manifest.json
tensorboard_projects/server/js/build/robots.txt
tensorboard_projects/server/js/build/static/css/2.73fc444d.chunk.css
tensorboard_projects/server/js/build/static/css/2.73fc444d.chunk.css.map
tensorboard_projects/server/js/build/static/css/main.e3871557.chunk.css
tensorboard_projects/server/js/build/static/css/main.e3871557.chunk.css.map
tensorboard_projects/server/js/build/static/js/2.5ca1339c.chunk.js
tensorboard_projects/server/js/build/static/js/2.5ca1339c.chunk.js.LICENSE.txt
tensorboard_projects/server/js/build/static/js/2.5ca1339c.chunk.js.map
tensorboard_projects/server/js/build/static/js/main.12fd3394.chunk.js
tensorboard_projects/server/js/build/static/js/main.12fd3394.chunk.js.LICENSE.txt
tensorboard_projects/server/js/build/static/js/main.12fd3394.chunk.js.map
tensorboard_projects/server/js/build/static/js/runtime-main.920dd924.js
tensorboard_projects/server/js/build/static/js/runtime-main.920dd924.js.map
tensorboard_projects/store/__init__.py
tensorboard_projects/store/file_store.py
tensorboard_projects/store/test_file_store.py
tensorboard_projects/types/__init__.py
tensorboard_projects/types/initialization.py
tensorboard_projects/utils/__init__.py
tensorboard_projects/utils/cli_args.py
tensorboard_projects/utils/process.py
tensorboard_projects-0.0.1rc10.dist-info/LICENSE
tensorboard_projects-0.0.1rc10.dist-info/METADATA
tensorboard_projects-0.0.1rc10.dist-info/WHEEL
tensorboard_projects-0.0.1rc10.dist-info/entry_points.txt
tensorboard_projects-0.0.1rc10.dist-info/top_level.txt
tensorboard_projects-0.0.1rc10.dist-info/RECORD
