Metadata-Version: 2.1
Name: tensorboard-projects
Version: 0.0.1rc10
Summary: Tensorboard Projects: A management UI for Tensorboard runs
Home-page: https://github.com/jverre/tensorboard-projects
Author: Jacques Verré
License: MIT
Platform: UNKNOWN
Requires-Python: >=2.7,!= 3.0.*,!= 3.1.*,!= 3.2.*,!= 3.3.*,!= 3.4.*,!= 3.5.*
Requires-Dist: click (>=7.0Flask)
Requires-Dist: flask-cors
Requires-Dist: gunicorn
Requires-Dist: tensorboard
